clean_transcribe-1.0.1.dist-info/licenses/LICENSE
clean_transcriber/__init__.py
clean_transcriber/cleaner.py
clean_transcriber/downloader.py
clean_transcriber/extractor.py
clean_transcriber/formatter.py
clean_transcriber/main.py
clean_transcriber/openai_api.py
clean_transcriber/transcriber.py
clean_transcriber/trimmer.py
clean_transcriber/voxtral_api.py
clean_transcriber/voxtral_local.py
clean_transcribe-1.0.1.dist-info/METADATA
clean_transcribe-1.0.1.dist-info/WHEEL
clean_transcribe-1.0.1.dist-info/entry_points.txt
clean_transcribe-1.0.1.dist-info/top_level.txt
clean_transcribe-1.0.1.dist-info/RECORD
