Metadata-Version: 2.4
Name: clean-transcribe
Version: 1.0.1
Summary: A simple CLI to transcribe Youtube videos or local audio/video files and produce easy-to-use transcripts for analysis, reading, or subtitles.
Home-page: https://github.com/itsmevictor/clean-transcribe
Author: Victor Kreitmann
Author-email: victor.kreitmann@gmail.com
Project-URL: Bug Reports, https://github.com/itsmevictor/clean-transcribe/issues
Project-URL: Source, https://github.com/itsmevictor/clean-transcribe
Keywords: youtube transcription whisper ai cleaning subtitles srt vtt
Classifier: Development Status :: 4 - Beta
Classifier: Intended Audience :: Developers
Classifier: Intended Audience :: End Users/Desktop
Classifier: License :: OSI Approved :: MIT License
Classifier: Operating System :: OS Independent
Classifier: Programming Language :: Python :: 3
Classifier: Programming Language :: Python :: 3.7
Classifier: Programming Language :: Python :: 3.8
Classifier: Programming Language :: Python :: 3.9
Classifier: Programming Language :: Python :: 3.10
Classifier: Programming Language :: Python :: 3.11
Classifier: Programming Language :: Python :: 3.12
Classifier: Topic :: Multimedia :: Sound/Audio :: Speech
Classifier: Topic :: Text Processing :: Linguistic
Classifier: Topic :: Utilities
Requires-Python: >=3.7
License-File: LICENSE
Requires-Dist: yt-dlp>=2023.12.30
Requires-Dist: openai-whisper>=20231117
Requires-Dist: click>=8.1.7
Requires-Dist: click-option-group>=0.5.6
Requires-Dist: pydub>=0.25.1
Requires-Dist: ffmpeg-python>=0.2.0
Requires-Dist: tqdm>=4.66.1
Requires-Dist: llm>=0.13.0
Requires-Dist: llm-gemini>=0.1.0
Requires-Dist: openai>=1.0.0
Requires-Dist: requests>=2.25.0
Requires-Dist: mistral-common>=1.8.1
Requires-Dist: timm
Requires-Dist: librosa
Dynamic: author
Dynamic: author-email
Dynamic: classifier
Dynamic: description
Dynamic: description-content-type
Dynamic: home-page
Dynamic: keywords
Dynamic: license-file
Dynamic: project-url
Dynamic: requires-dist
Dynamic: requires-python
Dynamic: summary
